tsgxr/__init__.py
tsgxr/_version.py
tsgxr/cli.py
tsgxr/read.py
tsgxr/util.py
tsgxr-0.2.5.dist-info/LICENSE
tsgxr-0.2.5.dist-info/METADATA
tsgxr-0.2.5.dist-info/WHEEL
tsgxr-0.2.5.dist-info/entry_points.txt
tsgxr-0.2.5.dist-info/top_level.txt
tsgxr-0.2.5.dist-info/RECORD
