Metadata-Version: 2.1
Name: tsgxr
Version: 0.2.5
Summary: A tool for reading TSG spectra data into Xarray.
Home-page: https://github.com/CSIRO-GeoscienceAnalytics/tsg-xr
Author: Morgan Williams
Author-email: morgan.williams@csiro.au
License: MIT
Project-URL: Code, https://github.com/CSIRO-GeoscienceAnalytics/tsg-xr
Project-URL: Issue tracker, https://github.com/CSIRO-GeoscienceAnalytics/tsg-xr/issues
Keywords: TSG,spectra
Classifier: Intended Audience :: Science/Research
Classifier: Natural Language :: English
Classifier: Programming Language :: Python :: 3 :: Only
Classifier: Programming Language :: Python :: 3.10
Classifier: Topic :: Scientific/Engineering
Classifier: Topic :: Software Development :: Libraries :: Python Modules
License-File: LICENSE
Requires-Dist: numpy
Requires-Dist: xarray
Requires-Dist: zarr
Requires-Dist: pandas
Requires-Dist: pytsg (>=0.2.8)
Requires-Dist: typer
Provides-Extra: dev
Requires-Dist: pytest ; extra == 'dev'
Requires-Dist: pytest-cov ; extra == 'dev'
Requires-Dist: coverage ; extra == 'dev'
Requires-Dist: versioneer ; extra == 'dev'
Requires-Dist: black ; extra == 'dev'
Requires-Dist: twine ; extra == 'dev'
Provides-Extra: plot
Requires-Dist: matplotlib ; extra == 'plot'
